{"matchId":1694440,"label":"Portugal - France, 1 - 0 (E)","teamsInfo":{"4418":{"city":"Paris","name":"France","wyId":4418,"officialName":"France","area":{"name":"France","id":250,"alpha3code":"FRA","alpha2code":"FR"},"type":"national"},"9905":{"city":"Lisboa","name":"Portugal","wyId":9905,"officialName":"Portugal","area":{"name":"Portugal","id":620,"alpha3code":"PRT","alpha2code":"PT"},"type":"national"}},"matchInfo":{"winner":9905,"homeAway":{"home":9905,"away":4418},"competitionId":102,"gameweek":0,"duration":"ExtraTime","seasonId":9291,"roundId":4165474,"groupName":"Group F","status":"Played","venue":"Stade de France","dateutc":"2016-07-10 19:00:00","homeAwayId":{"9905":"home","4418":"away"}},"nodes":{"9905":[{"id":"7926","pos":"7926","shortName":["Nani"],"currentNationalTeamId":9905,"averagePos":[60.8125,42.72916793823242],"metrics":{"outDegree":22.0,"inDegree":26.0,"currentFlowBetweennessCentrality":-0.09335119140945272,"katzCentrality":1.4737067500996786,"degree":48.0,"alphaCentrality":1.4737067500996786,"betweennessCentrality":0.14157407407407405,"localClusteringCoefficient":0.8888888888888888,"closenessCentrality":0.4,"eigenvectorCentrality":1.8229888913521246E-5}},{"id":"70389","pos":"70389","shortName":["C\u00e9dric Soares"],"currentNationalTeamId":9905,"averagePos":[88.64616,51.96923065185547],"metrics":{"outDegree":27.0,"inDegree":38.0,"currentFlowBetweennessCentrality":-0.09516576401179609,"katzCentrality":1.6665119256752021,"degree":65.0,"alphaCentrality":1.6665119256752021,"betweennessCentrality":0.16490740740740742,"localClusteringCoefficient":0.8888888888888888,"closenessCentrality":0.5,"eigenvectorCentrality":2.410528098204971E-5}},{"id":"7040370093","pos":"7040370093","shortName":["Jo\u00e3o Moutinho","Adrien Silva"],"currentNationalTeamId":9905,"averagePos":[42.679245,50.849056243896484],"metrics":{"outDegree":51.0,"inDegree":55.0,"currentFlowBetweennessCentrality":-0.1632082333502008,"katzCentrality":2.0031015880857588,"degree":106.0,"alphaCentrality":2.0031015880857588,"betweennessCentrality":0.0,"localClusteringCoefficient":0.9305555555555556,"closenessCentrality":0.21739130434782608,"eigenvectorCentrality":3.86884290238686E-5}},{"id":"325973322","pos":"325973322","shortName":["Cristiano Ronaldo","Ricardo Quaresma"],"currentNationalTeamId":9905,"averagePos":[62.018867,38.39622497558594],"metrics":{"outDegree":25.0,"inDegree":28.0,"currentFlowBetweennessCentrality":-0.035182749273691194,"katzCentrality":1.4803850229995859,"degree":53.0,"alphaCentrality":1.4803850229995859,"betweennessCentrality":0.06685185185185186,"localClusteringCoefficient":0.8777777777777778,"closenessCentrality":0.4,"eigenvectorCentrality":1.703847045520173E-5}},{"id":"37762","pos":"37762","shortName":["William Carvalho"],"currentNationalTeamId":9905,"averagePos":[46.663715,58.11504364013672],"metrics":{"outDegree":59.0,"inDegree":54.0,"currentFlowBetweennessCentrality":-0.004166780268118058,"katzCentrality":1.9773708520445104,"degree":113.0,"alphaCentrality":1.9773708520445104,"betweennessCentrality":0.002777777777777778,"localClusteringCoefficient":0.8666666666666667,"closenessCentrality":0.2222222222222222,"eigenvectorCentrality":3.6993257253792714E-5}},{"id":"70134","pos":"70134","shortName":["Rui Patr\u00edcio"],"currentNationalTeamId":9905,"averagePos":[50.148937,86.44680881500244],"metrics":{"outDegree":28.0,"inDegree":19.0,"currentFlowBetweennessCentrality":0.028340168435605412,"katzCentrality":1.3556131462805463,"degree":47.0,"alphaCentrality":1.3556131462805463,"betweennessCentrality":0.10370370370370369,"localClusteringCoefficient":0.9305555555555556,"closenessCentrality":0.37037037037037035,"eigenvectorCentrality":1.3864953299102541E-5}},{"id":"8126","pos":"8126","shortName":["Jos\u00e9 Fonte"],"currentNationalTeamId":9905,"averagePos":[27.17213,70.36065483093262],"metrics":{"outDegree":62.0,"inDegree":60.0,"currentFlowBetweennessCentrality":-0.10032651344671188,"katzCentrality":2.069718976820519,"degree":122.0,"alphaCentrality":2.069718976820519,"betweennessCentrality":0.08962962962962963,"localClusteringCoefficient":0.8777777777777778,"closenessCentrality":0.4166666666666667,"eigenvectorCentrality":4.0321059338262937E-5}},{"id":"3305","pos":"3305","shortName":["Pepe"],"currentNationalTeamId":9905,"averagePos":[70.16,68.38666725158691],"metrics":{"outDegree":38.0,"inDegree":37.0,"currentFlowBetweennessCentrality":-0.0651687649737444,"katzCentrality":1.661776849415099,"degree":75.0,"alphaCentrality":1.661776849415099,"betweennessCentrality":0.06129629629629629,"localClusteringCoefficient":0.8777777777777778,"closenessCentrality":0.38461538461538464,"eigenvectorCentrality":2.455110843698618E-5}},{"id":"28907","pos":"28907","shortName":["Rapha\u00ebl Guerreiro"],"currentNationalTeamId":9905,"averagePos":[11.775701,53.01869201660156],"metrics":{"outDegree":52.0,"inDegree":55.0,"currentFlowBetweennessCentrality":-0.03660289991679436,"katzCentrality":2.035583312001979,"degree":107.0,"alphaCentrality":2.035583312001979,"betweennessCentrality":0.03981481481481482,"localClusteringCoefficient":0.8777777777777778,"closenessCentrality":0.3333333333333333,"eigenvectorCentrality":4.136574868574472E-5}},{"id":"70410258162","pos":"70410258162","shortName":["Renato Sanches","\u00c9der"],"currentNationalTeamId":9905,"averagePos":[53.623375,53.14285659790039],"metrics":{"outDegree":38.0,"inDegree":39.0,"currentFlowBetweennessCentrality":0.020887755989982586,"katzCentrality":1.7042973904580498,"degree":77.0,"alphaCentrality":1.7042973904580498,"betweennessCentrality":0.008333333333333333,"localClusteringCoefficient":0.8555555555555555,"closenessCentrality":0.38461538461538464,"eigenvectorCentrality":2.687500851081008E-5}},{"id":"70965","pos":"70965","shortName":["Jo\u00e3o M\u00e1rio"],"currentNationalTeamId":9905,"averagePos":[33.724136,44.747127532958984],"metrics":{"outDegree":48.0,"inDegree":39.0,"currentFlowBetweennessCentrality":-0.017926120151022986,"katzCentrality":1.7395095173534583,"degree":87.0,"alphaCentrality":1.7395095173534583,"betweennessCentrality":0.026111111111111113,"localClusteringCoefficient":0.8666666666666667,"closenessCentrality":0.3448275862068966,"eigenvectorCentrality":3.0012849185479577E-5}}],"4418":[{"id":"7858","pos":"7858","shortName":["B. Sagna"],"currentNationalTeamId":4418,"averagePos":[86.666664,42.11827850341797],"metrics":{"outDegree":45.0,"inDegree":48.0,"currentFlowBetweennessCentrality":-0.11124390594524279,"katzCentrality":2.607609417727517,"degree":93.0,"alphaCentrality":2.607609417727517,"betweennessCentrality":0.08349206349206349,"localClusteringCoefficient":0.7888888888888889,"closenessCentrality":0.25,"eigenvectorCentrality":9.432342332211534E-5}},{"id":"7855","pos":"7855","shortName":["L. Koscielny"],"currentNationalTeamId":4418,"averagePos":[67.23529,63.183006286621094],"metrics":{"outDegree":85.0,"inDegree":68.0,"currentFlowBetweennessCentrality":-0.1026734666944028,"katzCentrality":3.5484762139754933,"degree":153.0,"alphaCentrality":3.5484762139754933,"betweennessCentrality":0.11145502645502646,"localClusteringCoefficient":0.7777777777777778,"closenessCentrality":0.4,"eigenvectorCentrality":1.560267691156513E-4}},{"id":"7936","pos":"7936","shortName":["P. Pogba"],"currentNationalTeamId":4418,"averagePos":[60.688118,51.56435775756836],"metrics":{"outDegree":102.0,"inDegree":100.0,"currentFlowBetweennessCentrality":-0.00360102253575127,"katzCentrality":4.425368878303985,"degree":202.0,"alphaCentrality":4.425368878303985,"betweennessCentrality":0.005555555555555556,"localClusteringCoefficient":0.7555555555555555,"closenessCentrality":0.35714285714285715,"eigenvectorCentrality":2.0360062301257004E-4}},{"id":"25397","pos":"25397","shortName":["S. Umtiti"],"currentNationalTeamId":4418,"averagePos":[31.536945,62.497535705566406],"metrics":{"outDegree":106.0,"inDegree":97.0,"currentFlowBetweennessCentrality":0.03765464827793622,"katzCentrality":4.364925072921344,"degree":203.0,"alphaCentrality":4.364925072921344,"betweennessCentrality":0.08650793650793649,"localClusteringCoefficient":0.8055555555555556,"closenessCentrality":0.30303030303030304,"eigenvectorCentrality":2.015315700878132E-4}},{"id":"2601025575","pos":"2601025575","shortName":["O. Giroud","A. Gignac"],"currentNationalTeamId":4418,"averagePos":[43.454544,20.86363983154297],"metrics":{"outDegree":9.0,"inDegree":13.0,"currentFlowBetweennessCentrality":-0.09295914984078654,"katzCentrality":1.3939333190916277,"degree":22.0,"alphaCentrality":1.3939333190916277,"betweennessCentrality":0.1678042328042328,"localClusteringCoefficient":0.9464285714285714,"closenessCentrality":0.4,"eigenvectorCentrality":2.1909215159955583E-5}},{"id":"25381","pos":"25381","shortName":["H. Lloris"],"currentNationalTeamId":4418,"averagePos":[48.0,90.0],"metrics":{"outDegree":7.0,"inDegree":4.0,"currentFlowBetweennessCentrality":0.0058728444867790375,"katzCentrality":1.1670341598289005,"degree":11.0,"alphaCentrality":1.1670341598289005,"betweennessCentrality":0.05350088183421516,"localClusteringCoefficient":1.0,"closenessCentrality":0.3333333333333333,"eigenvectorCentrality":1.0689958327408608E-5}},{"id":"7915","pos":"7915","shortName":["P. Evra"],"currentNationalTeamId":4418,"averagePos":[12.663366,42.53465270996094],"metrics":{"outDegree":52.0,"inDegree":49.0,"currentFlowBetweennessCentrality":-0.08974986159903325,"katzCentrality":2.734161332024555,"degree":101.0,"alphaCentrality":2.734161332024555,"betweennessCentrality":0.09732363315696649,"localClusteringCoefficient":0.875,"closenessCentrality":0.38461538461538464,"eigenvectorCentrality":1.0374706540612041E-4}},{"id":"25804134513","pos":"25804134513","shortName":["A. Martial","M. Sissoko"],"currentNationalTeamId":4418,"averagePos":[65.21951,35.51219177246094],"metrics":{"outDegree":38.0,"inDegree":44.0,"currentFlowBetweennessCentrality":0.00975992635051139,"katzCentrality":2.474922006758698,"degree":82.0,"alphaCentrality":2.474922006758698,"betweennessCentrality":0.22999999999999998,"localClusteringCoefficient":0.7555555555555555,"closenessCentrality":0.3333333333333333,"eigenvectorCentrality":8.645344798004722E-5}},{"id":"25437","pos":"25437","shortName":["B. Matuidi"],"currentNationalTeamId":4418,"averagePos":[34.760868,48.87681198120117],"metrics":{"outDegree":68.0,"inDegree":70.0,"currentFlowBetweennessCentrality":-0.05710690109772692,"katzCentrality":3.484884650419268,"degree":138.0,"alphaCentrality":3.484884650419268,"betweennessCentrality":0.013902116402116402,"localClusteringCoefficient":0.875,"closenessCentrality":0.23255813953488372,"eigenvectorCentrality":1.493819148363969E-4}},{"id":"23113925714","pos":"23113925714","shortName":["D. Payet","K. Coman"],"currentNationalTeamId":4418,"averagePos":[30.849558,32.19468688964844],"metrics":{"outDegree":49.0,"inDegree":64.0,"currentFlowBetweennessCentrality":-0.14725083522554686,"katzCentrality":3.1272275164898575,"degree":113.0,"alphaCentrality":3.1272275164898575,"betweennessCentrality":0.0,"localClusteringCoefficient":0.8888888888888888,"closenessCentrality":0.3225806451612903,"eigenvectorCentrality":1.2414263230883034E-4}},{"id":"3682","pos":"3682","shortName":["A. Griezmann"],"currentNationalTeamId":4418,"averagePos":[49.22619,38.595237731933594],"metrics":{"outDegree":40.0,"inDegree":44.0,"currentFlowBetweennessCentrality":-0.06735796954455309,"katzCentrality":2.4548399758061996,"degree":84.0,"alphaCentrality":2.4548399758061996,"betweennessCentrality":0.0022222222222222222,"localClusteringCoefficient":0.875,"closenessCentrality":0.2702702702702703,"eigenvectorCentrality":8.460892205990263E-5}}]},"links":{"9905":[{"source":"70134","target":"7926","teamId":9905,"value":1},{"source":"325973322","target":"28907","teamId":9905,"value":1},{"source":"70389","target":"70965","teamId":9905,"value":1},{"source":"70389","target":"37762","teamId":9905,"value":1},{"source":"325973322","target":"70134","teamId":9905,"value":1},{"source":"8126","target":"70389","teamId":9905,"value":1},{"source":"70965","target":"70134","teamId":9905,"value":1},{"source":"28907","target":"70134","teamId":9905,"value":1},{"source":"28907","target":"3305","teamId":9905,"value":1},{"source":"70389","target":"70134","teamId":9905,"value":1},{"source":"8126","target":"325973322","teamId":9905,"value":1},{"source":"70965","target":"3305","teamId":9905,"value":1},{"source":"70389","target":"28907","teamId":9905,"value":1},{"source":"70410258162","target":"70134","teamId":9905,"value":1},{"source":"7926","target":"8126","teamId":9905,"value":1},{"source":"3305","target":"7926","teamId":9905,"value":1},{"source":"7926","target":"3305","teamId":9905,"value":1},{"source":"28907","target":"7926","teamId":9905,"value":2},{"source":"3305","target":"28907","teamId":9905,"value":2},{"source":"28907","target":"325973322","teamId":9905,"value":2},{"source":"70410258162","target":"70389","teamId":9905,"value":2},{"source":"70134","target":"325973322","teamId":9905,"value":2},{"source":"70410258162","target":"3305","teamId":9905,"value":2},{"source":"325973322","target":"7926","teamId":9905,"value":2},{"source":"70134","target":"70410258162","teamId":9905,"value":2},{"source":"8126","target":"70965","teamId":9905,"value":2},{"source":"3305","target":"325973322","teamId":9905,"value":2},{"source":"3305","target":"70410258162","teamId":9905,"value":2},{"source":"3305","target":"70965","teamId":9905,"value":2},{"source":"70410258162","target":"7926","teamId":9905,"value":2},{"source":"70134","target":"28907","teamId":9905,"value":2},{"source":"7926","target":"37762","teamId":9905,"value":2},{"source":"325973322","target":"8126","teamId":9905,"value":2},{"source":"70410258162","target":"325973322","teamId":9905,"value":2},{"source":"325973322","target":"70965","teamId":9905,"value":2},{"source":"7040370093","target":"70389","teamId":9905,"value":3},{"source":"7926","target":"70410258162","teamId":9905,"value":3},{"source":"70134","target":"37762","teamId":9905,"value":3},{"source":"37762","target":"325973322","teamId":9905,"value":3},{"source":"70389","target":"70410258162","teamId":9905,"value":3},{"source":"70389","target":"7040370093","teamId":9905,"value":3},{"source":"7926","target":"325973322","teamId":9905,"value":3},{"source":"70410258162","target":"70965","teamId":9905,"value":3},{"source":"70389","target":"7926","teamId":9905,"value":3},{"source":"7926","target":"70965","teamId":9905,"value":3},{"source":"37762","target":"7926","teamId":9905,"value":3},{"source":"325973322","target":"70410258162","teamId":9905,"value":3},{"source":"70965","target":"37762","teamId":9905,"value":3},{"source":"7926","target":"70389","teamId":9905,"value":4},{"source":"70965","target":"8126","teamId":9905,"value":4},{"source":"70410258162","target":"8126","teamId":9905,"value":4},{"source":"70965","target":"70389","teamId":9905,"value":4},{"source":"70965","target":"7926","teamId":9905,"value":4},{"source":"8126","target":"70410258162","teamId":9905,"value":4},{"source":"7040370093","target":"70965","teamId":9905,"value":4},{"source":"325973322","target":"70389","teamId":9905,"value":4},{"source":"70410258162","target":"28907","teamId":9905,"value":5},{"source":"7040370093","target":"70410258162","teamId":9905,"value":5},{"source":"3305","target":"70134","teamId":9905,"value":5},{"source":"7040370093","target":"3305","teamId":9905,"value":5},{"source":"28907","target":"70410258162","teamId":9905,"value":5},{"source":"28907","target":"37762","teamId":9905,"value":5},{"source":"37762","target":"70410258162","teamId":9905,"value":5},{"source":"325973322","target":"7040370093","teamId":9905,"value":5},{"source":"7926","target":"7040370093","teamId":9905,"value":5},{"source":"325973322","target":"37762","teamId":9905,"value":5},{"source":"7040370093","target":"37762","teamId":9905,"value":6},{"source":"70965","target":"7040370093","teamId":9905,"value":6},{"source":"70965","target":"325973322","teamId":9905,"value":6},{"source":"37762","target":"3305","teamId":9905,"value":6},{"source":"37762","target":"28907","teamId":9905,"value":7},{"source":"70134","target":"3305","teamId":9905,"value":7},{"source":"70389","target":"325973322","teamId":9905,"value":7},{"source":"3305","target":"8126","teamId":9905,"value":7},{"source":"70389","target":"3305","teamId":9905,"value":7},{"source":"8126","target":"3305","teamId":9905,"value":7},{"source":"3305","target":"37762","teamId":9905,"value":7},{"source":"70965","target":"70410258162","teamId":9905,"value":7},{"source":"8126","target":"7040370093","teamId":9905,"value":8},{"source":"70410258162","target":"37762","teamId":9905,"value":8},{"source":"37762","target":"70965","teamId":9905,"value":8},{"source":"37762","target":"7040370093","teamId":9905,"value":8},{"source":"7040370093","target":"7926","teamId":9905,"value":8},{"source":"70410258162","target":"7040370093","teamId":9905,"value":9},{"source":"8126","target":"70134","teamId":9905,"value":9},{"source":"7040370093","target":"28907","teamId":9905,"value":9},{"source":"37762","target":"8126","teamId":9905,"value":9},{"source":"37762","target":"70389","teamId":9905,"value":10},{"source":"3305","target":"70389","teamId":9905,"value":10},{"source":"70134","target":"8126","teamId":9905,"value":11},{"source":"28907","target":"8126","teamId":9905,"value":11},{"source":"28907","target":"7040370093","teamId":9905,"value":11},{"source":"7040370093","target":"8126","teamId":9905,"value":11},{"source":"70965","target":"28907","teamId":9905,"value":12},{"source":"28907","target":"70965","teamId":9905,"value":14},{"source":"8126","target":"37762","teamId":9905,"value":14},{"source":"8126","target":"28907","teamId":9905,"value":16}],"4418":[{"source":"7936","target":"2601025575","teamId":4418,"value":1},{"source":"25804134513","target":"25397","teamId":4418,"value":1},{"source":"25397","target":"25804134513","teamId":4418,"value":1},{"source":"7936","target":"25381","teamId":4418,"value":1},{"source":"25804134513","target":"25437","teamId":4418,"value":1},{"source":"7858","target":"25397","teamId":4418,"value":1},{"source":"7855","target":"2601025575","teamId":4418,"value":1},{"source":"2601025575","target":"7858","teamId":4418,"value":1},{"source":"25381","target":"25804134513","teamId":4418,"value":1},{"source":"2601025575","target":"7915","teamId":4418,"value":1},{"source":"7915","target":"7855","teamId":4418,"value":1},{"source":"25397","target":"7858","teamId":4418,"value":1},{"source":"2601025575","target":"25804134513","teamId":4418,"value":1},{"source":"7855","target":"3682","teamId":4418,"value":1},{"source":"7915","target":"2601025575","teamId":4418,"value":1},{"source":"25381","target":"7858","teamId":4418,"value":1},{"source":"7855","target":"25381","teamId":4418,"value":1},{"source":"7855","target":"7915","teamId":4418,"value":2},{"source":"3682","target":"7855","teamId":4418,"value":2},{"source":"7915","target":"7858","teamId":4418,"value":2},{"source":"3682","target":"2601025575","teamId":4418,"value":2},{"source":"23113925714","target":"25804134513","teamId":4418,"value":2},{"source":"25381","target":"7936","teamId":4418,"value":2},{"source":"25437","target":"2601025575","teamId":4418,"value":2},{"source":"25804134513","target":"7915","teamId":4418,"value":2},{"source":"23113925714","target":"7855","teamId":4418,"value":2},{"source":"25397","target":"25381","teamId":4418,"value":2},{"source":"7915","target":"7936","teamId":4418,"value":3},{"source":"25804134513","target":"2601025575","teamId":4418,"value":3},{"source":"23113925714","target":"7858","teamId":4418,"value":3},{"source":"23113925714","target":"2601025575","teamId":4418,"value":3},{"source":"7915","target":"25804134513","teamId":4418,"value":3},{"source":"25437","target":"25804134513","teamId":4418,"value":3},{"source":"3682","target":"7915","teamId":4418,"value":3},{"source":"25381","target":"25397","teamId":4418,"value":3},{"source":"23113925714","target":"3682","teamId":4418,"value":4},{"source":"3682","target":"25804134513","teamId":4418,"value":4},{"source":"3682","target":"25397","teamId":4418,"value":4},{"source":"25437","target":"7858","teamId":4418,"value":4},{"source":"3682","target":"25437","teamId":4418,"value":4},{"source":"7858","target":"3682","teamId":4418,"value":4},{"source":"25437","target":"3682","teamId":4418,"value":5},{"source":"7936","target":"7915","teamId":4418,"value":5},{"source":"25804134513","target":"7855","teamId":4418,"value":5},{"source":"3682","target":"7936","teamId":4418,"value":6},{"source":"25804134513","target":"7936","teamId":4418,"value":6},{"source":"25804134513","target":"7858","teamId":4418,"value":6},{"source":"25804134513","target":"23113925714","teamId":4418,"value":6},{"source":"2601025575","target":"23113925714","teamId":4418,"value":6},{"source":"23113925714","target":"7936","teamId":4418,"value":6},{"source":"25397","target":"3682","teamId":4418,"value":6},{"source":"7936","target":"3682","teamId":4418,"value":7},{"source":"7858","target":"25437","teamId":4418,"value":7},{"source":"7855","target":"25804134513","teamId":4418,"value":7},{"source":"3682","target":"7858","teamId":4418,"value":7},{"source":"23113925714","target":"25397","teamId":4418,"value":8},{"source":"23113925714","target":"25437","teamId":4418,"value":8},{"source":"25437","target":"25397","teamId":4418,"value":8},{"source":"7915","target":"23113925714","teamId":4418,"value":8},{"source":"3682","target":"23113925714","teamId":4418,"value":8},{"source":"25804134513","target":"3682","teamId":4418,"value":8},{"source":"7915","target":"3682","teamId":4418,"value":9},{"source":"7936","target":"23113925714","teamId":4418,"value":9},{"source":"7858","target":"25804134513","teamId":4418,"value":9},{"source":"25437","target":"7855","teamId":4418,"value":9},{"source":"7855","target":"7858","teamId":4418,"value":10},{"source":"7915","target":"25437","teamId":4418,"value":10},{"source":"7858","target":"7855","teamId":4418,"value":10},{"source":"25397","target":"7915","teamId":4418,"value":11},{"source":"25437","target":"23113925714","teamId":4418,"value":11},{"source":"7855","target":"25437","teamId":4418,"value":12},{"source":"25437","target":"7915","teamId":4418,"value":12},{"source":"23113925714","target":"7915","teamId":4418,"value":13},{"source":"7936","target":"25437","teamId":4418,"value":13},{"source":"7936","target":"25804134513","teamId":4418,"value":13},{"source":"7936","target":"7858","teamId":4418,"value":13},{"source":"7858","target":"7936","teamId":4418,"value":14},{"source":"25437","target":"7936","teamId":4418,"value":14},{"source":"7915","target":"25397","teamId":4418,"value":15},{"source":"7936","target":"7855","teamId":4418,"value":15},{"source":"25397","target":"25437","teamId":4418,"value":15},{"source":"25397","target":"23113925714","teamId":4418,"value":16},{"source":"7855","target":"7936","teamId":4418,"value":19},{"source":"25397","target":"7855","teamId":4418,"value":24},{"source":"7936","target":"25397","teamId":4418,"value":25},{"source":"25397","target":"7936","teamId":4418,"value":30},{"source":"7855","target":"25397","teamId":4418,"value":32}]},"stats":{"global":{"outDegree":{"min":7.0,"max":106.0},"passes":{"min":1,"max":32},"inDegree":{"min":4.0,"max":100.0},"currentFlowBetweennessCentrality":{"min":-0.1632082333502008,"max":0.03765464827793622},"katzCentrality":{"min":1.1670341598289005,"max":4.425368878303985},"degree":{"min":11.0,"max":203.0},"alphaCentrality":{"min":1.1670341598289005,"max":4.425368878303985},"betweennessCentrality":{"min":0.0,"max":0.22999999999999998},"localClusteringCoefficient":{"min":0.7555555555555555,"max":1.0},"closenessCentrality":{"min":0.21739130434782608,"max":0.5},"eigenvectorCentrality":{"min":1.0689958327408608E-5,"max":2.0360062301257004E-4}},"home":{"outDegree":{"min":22.0,"max":62.0},"averageClusteringCoefficient":0.8853535353535353,"algebraicConnectivity":41.58853524875389,"globalClusteringCoefficient":0.9811320754716981,"averageNodeConnectivity":8.327272727272728,"passes":{"min":1,"max":16},"inDegree":{"min":19.0,"max":60.0},"currentFlowBetweennessCentrality":{"min":-0.1632082333502008,"max":0.028340168435605412},"katzCentrality":{"min":1.3556131462805463,"max":2.069718976820519},"degree":{"min":47.0,"max":122.0},"alphaCentrality":{"min":1.3556131462805463,"max":2.069718976820519},"betweennessCentrality":{"min":0.0,"max":0.16490740740740742},"localClusteringCoefficient":{"min":0.8555555555555555,"max":0.9305555555555556},"closenessCentrality":{"min":0.21739130434782608,"max":0.5},"eigenvectorCentrality":{"min":1.3864953299102541E-5,"max":4.136574868574472E-5}},"away":{"outDegree":{"min":7.0,"max":106.0},"averageClusteringCoefficient":0.8494227994227994,"algebraicConnectivity":11.774484456987262,"globalClusteringCoefficient":0.9195979899497487,"averageNodeConnectivity":6.7272727272727275,"passes":{"min":1,"max":32},"inDegree":{"min":4.0,"max":100.0},"currentFlowBetweennessCentrality":{"min":-0.14725083522554686,"max":0.03765464827793622},"katzCentrality":{"min":1.1670341598289005,"max":4.425368878303985},"degree":{"min":11.0,"max":203.0},"alphaCentrality":{"min":1.1670341598289005,"max":4.425368878303985},"betweennessCentrality":{"min":0.0,"max":0.22999999999999998},"localClusteringCoefficient":{"min":0.7555555555555555,"max":1.0},"closenessCentrality":{"min":0.23255813953488372,"max":0.4},"eigenvectorCentrality":{"min":1.0689958327408608E-5,"max":2.0360062301257004E-4}}}}