{"matchId":2499768,"label":"West Bromwich Albion - West Ham United, 0 - 0","teamsInfo":{"1627":{"city":"West Bromwich","name":"West Bromwich Albion","wyId":1627,"officialName":"West Bromwich Albion FC","area":{"name":"England","id":"0","alpha3code":"XEN","alpha2code":""},"type":"club"},"1633":{"city":"London","name":"West Ham United","wyId":1633,"officialName":"West Ham United FC","area":{"name":"England","id":"0","alpha3code":"XEN","alpha2code":""},"type":"club"}},"matchInfo":{"winner":0,"homeAway":{"home":1627,"away":1633},"competitionId":364,"gameweek":5,"duration":"Regular","seasonId":181150,"roundId":4405654,"groupName":null,"status":"Played","venue":"The Hawthorns","dateutc":"2017-09-16 14:00:00","homeAwayId":{"1627":"home","1633":"away"}},"nodes":{"1633":[{"id":"8301","pos":"8301","shortName":["J. Hart"],"currentNationalTeamId":1633,"averagePos":[51.1,89.93333339691162]},{"id":"8313","pos":"8313","shortName":["P. Zabaleta"],"currentNationalTeamId":1633,"averagePos":[52.205128,47.871795654296875]},{"id":"8553","pos":"8553","shortName":["W. Reid"],"currentNationalTeamId":1633,"averagePos":[53.59813,63.2149543762207]},{"id":"8126","pos":"8126","shortName":["Jos\u00e9 Fonte"],"currentNationalTeamId":1633,"averagePos":[79.13178,56.1705436706543]},{"id":"37725","pos":"37725","shortName":["C. Kouyat\u00e9"],"currentNationalTeamId":1633,"averagePos":[38.294872,46.17948532104492]},{"id":"800514703","pos":"800514703","shortName":["M. Arnautovi\u0107","J. Collins"],"currentNationalTeamId":1633,"averagePos":[23.23913,53.293479919433594]},{"id":"255727941","pos":"255727941","shortName":["J. Hern\u00e1ndez","A. Ayew"],"currentNationalTeamId":1633,"averagePos":[53.92105,33.71052551269531]},{"id":"266107970","pos":"266107970","shortName":["A. Carroll","D. Sakho"],"currentNationalTeamId":1633,"averagePos":[47.363636,30.68181610107422]},{"id":"8582","pos":"8582","shortName":["A. Cresswell"],"currentNationalTeamId":1633,"averagePos":[12.492754,39.18840408325195]},{"id":"20620","pos":"20620","shortName":["Pedro Obiang"],"currentNationalTeamId":1633,"averagePos":[51.300972,47.16504669189453]},{"id":"8677","pos":"8677","shortName":["M. Antonio"],"currentNationalTeamId":1633,"averagePos":[58.227272,39.70454406738281]}],"1627":[{"id":"7914","pos":"7914","shortName":["J. Evans"],"currentNationalTeamId":1627,"averagePos":[32.717392,70.45652198791504]},{"id":"8374","pos":"8374","shortName":["J. Morrison"],"currentNationalTeamId":1627,"averagePos":[41.065216,42.91304397583008]},{"id":"8958","pos":"8958","shortName":["J. Rodriguez"],"currentNationalTeamId":1627,"averagePos":[52.31579,37.842105865478516]},{"id":"119951","pos":"119951","shortName":["Ahmed Hegazy"],"currentNationalTeamId":1627,"averagePos":[65.4,68.92000007629395]},{"id":"8314","pos":"8314","shortName":["G. Barry"],"currentNationalTeamId":1627,"averagePos":[45.615383,53.630767822265625]},{"id":"8360","pos":"8360","shortName":["C. Dawson"],"currentNationalTeamId":1627,"averagePos":[81.89189,52.08108139038086]},{"id":"85309414","pos":"85309414","shortName":["J. McClean","M. Phillips"],"currentNationalTeamId":1627,"averagePos":[21.821428,42.21428680419922]},{"id":"52817853","pos":"52817853","shortName":["A. Nyom","K. Gibbs"],"currentNationalTeamId":1627,"averagePos":[14.255814,51.1860466003418]},{"id":"25537","pos":"25537","shortName":["G. Krychowiak"],"currentNationalTeamId":1627,"averagePos":[65.17778,58.400001525878906]},{"id":"86868370","pos":"86868370","shortName":["H. Robson-Kanu","C. Brunt"],"currentNationalTeamId":1627,"averagePos":[67.875,42.57500076293945]},{"id":"8358","pos":"8358","shortName":["B. Foster"],"currentNationalTeamId":1627,"averagePos":[42.333332,87.94444465637207]}]},"links":{"1627":[{"source":"8360","target":"8374","teamId":1627,"value":1},{"source":"7914","target":"8360","teamId":1627,"value":1},{"source":"86868370","target":"8358","teamId":1627,"value":1},{"source":"86868370","target":"119951","teamId":1627,"value":1},{"source":"25537","target":"52817853","teamId":1627,"value":1},{"source":"8314","target":"8958","teamId":1627,"value":1},{"source":"8358","target":"8314","teamId":1627,"value":1},{"source":"25537","target":"7914","teamId":1627,"value":1},{"source":"8374","target":"8358","teamId":1627,"value":1},{"source":"8360","target":"85309414","teamId":1627,"value":1},{"source":"52817853","target":"8358","teamId":1627,"value":1},{"source":"85309414","target":"8314","teamId":1627,"value":1},{"source":"7914","target":"8958","teamId":1627,"value":1},{"source":"7914","target":"8374","teamId":1627,"value":1},{"source":"8958","target":"8314","teamId":1627,"value":1},{"source":"8374","target":"119951","teamId":1627,"value":1},{"source":"8360","target":"8314","teamId":1627,"value":1},{"source":"85309414","target":"7914","teamId":1627,"value":1},{"source":"86868370","target":"7914","teamId":1627,"value":1},{"source":"7914","target":"86868370","teamId":1627,"value":1},{"source":"8374","target":"8360","teamId":1627,"value":1},{"source":"8358","target":"52817853","teamId":1627,"value":1},{"source":"8360","target":"8358","teamId":1627,"value":1},{"source":"119951","target":"8958","teamId":1627,"value":1},{"source":"8374","target":"86868370","teamId":1627,"value":2},{"source":"8958","target":"8374","teamId":1627,"value":2},{"source":"8360","target":"7914","teamId":1627,"value":2},{"source":"85309414","target":"8374","teamId":1627,"value":2},{"source":"8958","target":"86868370","teamId":1627,"value":2},{"source":"8958","target":"8360","teamId":1627,"value":2},{"source":"7914","target":"119951","teamId":1627,"value":2},{"source":"25537","target":"8958","teamId":1627,"value":2},{"source":"52817853","target":"8958","teamId":1627,"value":2},{"source":"25537","target":"119951","teamId":1627,"value":2},{"source":"8360","target":"119951","teamId":1627,"value":2},{"source":"7914","target":"85309414","teamId":1627,"value":2},{"source":"25537","target":"8374","teamId":1627,"value":2},{"source":"119951","target":"8358","teamId":1627,"value":2},{"source":"8958","target":"52817853","teamId":1627,"value":2},{"source":"119951","target":"8374","teamId":1627,"value":2},{"source":"85309414","target":"8360","teamId":1627,"value":2},{"source":"8358","target":"119951","teamId":1627,"value":2},{"source":"119951","target":"8314","teamId":1627,"value":2},{"source":"119951","target":"86868370","teamId":1627,"value":2},{"source":"8374","target":"85309414","teamId":1627,"value":3},{"source":"52817853","target":"8374","teamId":1627,"value":3},{"source":"7914","target":"52817853","teamId":1627,"value":3},{"source":"25537","target":"85309414","teamId":1627,"value":3},{"source":"119951","target":"8360","teamId":1627,"value":3},{"source":"8360","target":"8958","teamId":1627,"value":3},{"source":"8360","target":"25537","teamId":1627,"value":3},{"source":"8314","target":"85309414","teamId":1627,"value":3},{"source":"25537","target":"8360","teamId":1627,"value":3},{"source":"8374","target":"25537","teamId":1627,"value":3},{"source":"119951","target":"25537","teamId":1627,"value":3},{"source":"86868370","target":"8360","teamId":1627,"value":3},{"source":"8314","target":"8374","teamId":1627,"value":4},{"source":"8358","target":"7914","teamId":1627,"value":4},{"source":"52817853","target":"7914","teamId":1627,"value":4},{"source":"8360","target":"86868370","teamId":1627,"value":4},{"source":"7914","target":"8358","teamId":1627,"value":4},{"source":"8314","target":"7914","teamId":1627,"value":4},{"source":"8314","target":"8360","teamId":1627,"value":4},{"source":"8314","target":"25537","teamId":1627,"value":4},{"source":"52817853","target":"85309414","teamId":1627,"value":5},{"source":"8374","target":"52817853","teamId":1627,"value":5},{"source":"52817853","target":"8314","teamId":1627,"value":5},{"source":"8314","target":"86868370","teamId":1627,"value":5},{"source":"85309414","target":"52817853","teamId":1627,"value":5},{"source":"25537","target":"8314","teamId":1627,"value":5},{"source":"86868370","target":"8314","teamId":1627,"value":5},{"source":"8314","target":"52817853","teamId":1627,"value":6},{"source":"25537","target":"86868370","teamId":1627,"value":6},{"source":"8374","target":"8314","teamId":1627,"value":6},{"source":"86868370","target":"8374","teamId":1627,"value":7},{"source":"7914","target":"8314","teamId":1627,"value":7},{"source":"7914","target":"25537","teamId":1627,"value":7}],"1633":[{"source":"8553","target":"8582","teamId":1633,"value":1},{"source":"20620","target":"266107970","teamId":1633,"value":1},{"source":"8313","target":"266107970","teamId":1633,"value":1},{"source":"8313","target":"8677","teamId":1633,"value":1},{"source":"8582","target":"8553","teamId":1633,"value":1},{"source":"8301","target":"8677","teamId":1633,"value":1},{"source":"8313","target":"8301","teamId":1633,"value":1},{"source":"255727941","target":"8313","teamId":1633,"value":1},{"source":"8301","target":"8582","teamId":1633,"value":1},{"source":"37725","target":"8677","teamId":1633,"value":1},{"source":"8677","target":"255727941","teamId":1633,"value":1},{"source":"37725","target":"266107970","teamId":1633,"value":1},{"source":"266107970","target":"8126","teamId":1633,"value":1},{"source":"800514703","target":"255727941","teamId":1633,"value":1},{"source":"255727941","target":"8126","teamId":1633,"value":1},{"source":"800514703","target":"266107970","teamId":1633,"value":1},{"source":"255727941","target":"800514703","teamId":1633,"value":1},{"source":"266107970","target":"8313","teamId":1633,"value":1},{"source":"8553","target":"8677","teamId":1633,"value":1},{"source":"266107970","target":"20620","teamId":1633,"value":1},{"source":"8553","target":"255727941","teamId":1633,"value":1},{"source":"800514703","target":"8313","teamId":1633,"value":2},{"source":"8301","target":"8126","teamId":1633,"value":2},{"source":"8553","target":"20620","teamId":1633,"value":2},{"source":"8126","target":"8582","teamId":1633,"value":2},{"source":"8677","target":"8582","teamId":1633,"value":2},{"source":"266107970","target":"8582","teamId":1633,"value":2},{"source":"8313","target":"255727941","teamId":1633,"value":2},{"source":"8582","target":"255727941","teamId":1633,"value":2},{"source":"8677","target":"8313","teamId":1633,"value":2},{"source":"8582","target":"266107970","teamId":1633,"value":2},{"source":"8301","target":"8313","teamId":1633,"value":2},{"source":"8313","target":"8582","teamId":1633,"value":2},{"source":"8553","target":"37725","teamId":1633,"value":2},{"source":"20620","target":"800514703","teamId":1633,"value":3},{"source":"8126","target":"8677","teamId":1633,"value":3},{"source":"255727941","target":"37725","teamId":1633,"value":3},{"source":"8301","target":"800514703","teamId":1633,"value":3},{"source":"800514703","target":"8301","teamId":1633,"value":3},{"source":"37725","target":"8553","teamId":1633,"value":3},{"source":"255727941","target":"8553","teamId":1633,"value":3},{"source":"800514703","target":"8677","teamId":1633,"value":3},{"source":"800514703","target":"37725","teamId":1633,"value":3},{"source":"8677","target":"8553","teamId":1633,"value":3},{"source":"8126","target":"266107970","teamId":1633,"value":3},{"source":"20620","target":"8677","teamId":1633,"value":4},{"source":"8677","target":"37725","teamId":1633,"value":4},{"source":"8313","target":"800514703","teamId":1633,"value":4},{"source":"8126","target":"8301","teamId":1633,"value":4},{"source":"8126","target":"255727941","teamId":1633,"value":4},{"source":"266107970","target":"800514703","teamId":1633,"value":4},{"source":"8677","target":"8126","teamId":1633,"value":4},{"source":"8553","target":"8301","teamId":1633,"value":4},{"source":"8126","target":"37725","teamId":1633,"value":4},{"source":"20620","target":"255727941","teamId":1633,"value":4},{"source":"8301","target":"266107970","teamId":1633,"value":4},{"source":"255727941","target":"8677","teamId":1633,"value":4},{"source":"8677","target":"20620","teamId":1633,"value":5},{"source":"8582","target":"8677","teamId":1633,"value":5},{"source":"255727941","target":"20620","teamId":1633,"value":5},{"source":"8582","target":"8301","teamId":1633,"value":5},{"source":"37725","target":"8313","teamId":1633,"value":5},{"source":"800514703","target":"8126","teamId":1633,"value":5},{"source":"37725","target":"255727941","teamId":1633,"value":5},{"source":"8582","target":"800514703","teamId":1633,"value":5},{"source":"8313","target":"37725","teamId":1633,"value":6},{"source":"37725","target":"8582","teamId":1633,"value":6},{"source":"8582","target":"37725","teamId":1633,"value":6},{"source":"8313","target":"20620","teamId":1633,"value":6},{"source":"8313","target":"8126","teamId":1633,"value":6},{"source":"20620","target":"8313","teamId":1633,"value":6},{"source":"37725","target":"20620","teamId":1633,"value":6},{"source":"20620","target":"8582","teamId":1633,"value":6},{"source":"37725","target":"800514703","teamId":1633,"value":6},{"source":"8126","target":"800514703","teamId":1633,"value":6},{"source":"800514703","target":"8553","teamId":1633,"value":7},{"source":"8582","target":"20620","teamId":1633,"value":7},{"source":"20620","target":"8553","teamId":1633,"value":8},{"source":"8553","target":"8313","teamId":1633,"value":8},{"source":"800514703","target":"20620","teamId":1633,"value":8},{"source":"37725","target":"8126","teamId":1633,"value":8},{"source":"20620","target":"37725","teamId":1633,"value":9},{"source":"8313","target":"8553","teamId":1633,"value":9},{"source":"8126","target":"20620","teamId":1633,"value":10},{"source":"20620","target":"8126","teamId":1633,"value":12},{"source":"8553","target":"800514703","teamId":1633,"value":13},{"source":"8126","target":"8313","teamId":1633,"value":13},{"source":"800514703","target":"8582","teamId":1633,"value":14},{"source":"8126","target":"8553","teamId":1633,"value":16},{"source":"8553","target":"8126","teamId":1633,"value":25}]},"stats":{"global":{"passes":{"min":1,"max":25}},"home":{"passes":{"min":1,"max":7}},"away":{"passes":{"min":1,"max":25}}}}