{"matchId":2500965,"label":"Troyes - PSG, 0 - 2","teamsInfo":{"3767":{"city":"Paris","name":"PSG","wyId":3767,"officialName":"Paris Saint-Germain FC","area":{"name":"France","id":"250","alpha3code":"FRA","alpha2code":"FR"},"type":"club"},"3795":{"city":"Troyes","name":"Troyes","wyId":3795,"officialName":"Esp\\u00e9rance Sportive Troyes Aube Champagne","area":{"name":"France","id":"250","alpha3code":"FRA","alpha2code":"FR"},"type":"club"}},"matchInfo":{"winner":3767,"homeAway":{"home":3795,"away":3767},"competitionId":412,"gameweek":28,"duration":"Regular","seasonId":181189,"roundId":4405655,"groupName":null,"status":"Played","venue":"Stade de l'Aube","dateutc":"2018-03-03 16:00:00","homeAwayId":{"3795":"home","3767":"away"}},"nodes":{"3767":[{"id":"33343314","pos":"33343314","shortName":["Dani Alves","\u00c1. di Mar\u00eda"],"currentNationalTeamId":3767,"averagePos":[82.986755,35.0794677734375]},{"id":"231138","pos":"231138","shortName":["P. Kimpembe"],"currentNationalTeamId":3767,"averagePos":[32.379845,59.89922332763672]},{"id":"20394","pos":"20394","shortName":["Thiago Silva"],"currentNationalTeamId":3767,"averagePos":[68.86452,57.10322570800781]},{"id":"25439209117","pos":"25439209117","shortName":["A. Rabiot","T. Motta"],"currentNationalTeamId":3767,"averagePos":[44.744564,47.15217208862305]},{"id":"37824","pos":"37824","shortName":["T. Meunier"],"currentNationalTeamId":3767,"averagePos":[89.19718,42.93661880493164]},{"id":"356237471774","pos":"356237471774","shortName":["G. Lo Celso","T. Weah"],"currentNationalTeamId":3767,"averagePos":[60.717556,41.816795349121094]},{"id":"25418","pos":"25418","shortName":["A. Ar\u00e9ola"],"currentNationalTeamId":3767,"averagePos":[51.84375,85.3125]},{"id":"14862","pos":"14862","shortName":["J. Draxler"],"currentNationalTeamId":3767,"averagePos":[47.0,40.68674850463867]},{"id":"347200","pos":"347200","shortName":["C. Nkunku"],"currentNationalTeamId":3767,"averagePos":[22.907894,39.72368240356445]},{"id":"134540","pos":"134540","shortName":["L. Kurzawa"],"currentNationalTeamId":3767,"averagePos":[13.109756,42.85365676879883]},{"id":"3315","pos":"3315","shortName":["L. Diarra"],"currentNationalTeamId":3767,"averagePos":[51.048485,50.33333206176758]}],"3795":[{"id":"295761","pos":"295761","shortName":["S. Grandsir"],"currentNationalTeamId":3795,"averagePos":[55.02778,39.19444274902344]},{"id":"112377","pos":"112377","shortName":["O. Vizcarrondo"],"currentNationalTeamId":3795,"averagePos":[59.64706,63.588233947753906]},{"id":"25616149053","pos":"25616149053","shortName":["C. Ben Saada","R. Walter"],"currentNationalTeamId":3795,"averagePos":[32.511627,52.16279220581055]},{"id":"2886625891","pos":"2886625891","shortName":["B. Nivet","K. Azamoum"],"currentNationalTeamId":3795,"averagePos":[58.53125,41.71875]},{"id":"28314","pos":"28314","shortName":["C. H\u00e9relle"],"currentNationalTeamId":3795,"averagePos":[26.630434,68.95652198791504]},{"id":"209207","pos":"209207","shortName":["J. Obiang"],"currentNationalTeamId":3795,"averagePos":[14.285714,47.224491119384766]},{"id":"382275243","pos":"382275243","shortName":["S. Khaoui","Suk Hyun-Jun"],"currentNationalTeamId":3795,"averagePos":[62.9,43.04999923706055]},{"id":"29641","pos":"29641","shortName":["B. Pel\u00e9"],"currentNationalTeamId":3795,"averagePos":[23.175,36.79999923706055]},{"id":"26433","pos":"26433","shortName":["J. Cordoval"],"currentNationalTeamId":3795,"averagePos":[88.29032,52.0]},{"id":"25521","pos":"25521","shortName":["E. Zelazny"],"currentNationalTeamId":3795,"averagePos":[42.133335,84.13333320617676]},{"id":"25937","pos":"25937","shortName":["F. Bellugou"],"currentNationalTeamId":3795,"averagePos":[46.361702,58.53191375732422]}]},"links":{"3795":[{"source":"25521","target":"26433","teamId":3795,"value":1},{"source":"26433","target":"25616149053","teamId":3795,"value":1},{"source":"2886625891","target":"25937","teamId":3795,"value":1},{"source":"26433","target":"29641","teamId":3795,"value":1},{"source":"26433","target":"25521","teamId":3795,"value":1},{"source":"209207","target":"112377","teamId":3795,"value":1},{"source":"2886625891","target":"28314","teamId":3795,"value":1},{"source":"25521","target":"25937","teamId":3795,"value":1},{"source":"25616149053","target":"382275243","teamId":3795,"value":1},{"source":"382275243","target":"25937","teamId":3795,"value":1},{"source":"295761","target":"112377","teamId":3795,"value":1},{"source":"112377","target":"2886625891","teamId":3795,"value":1},{"source":"28314","target":"2886625891","teamId":3795,"value":1},{"source":"112377","target":"25616149053","teamId":3795,"value":1},{"source":"25616149053","target":"112377","teamId":3795,"value":1},{"source":"26433","target":"28314","teamId":3795,"value":1},{"source":"2886625891","target":"25616149053","teamId":3795,"value":1},{"source":"382275243","target":"26433","teamId":3795,"value":1},{"source":"209207","target":"382275243","teamId":3795,"value":1},{"source":"295761","target":"209207","teamId":3795,"value":1},{"source":"26433","target":"25937","teamId":3795,"value":1},{"source":"209207","target":"25521","teamId":3795,"value":1},{"source":"25937","target":"112377","teamId":3795,"value":1},{"source":"2886625891","target":"29641","teamId":3795,"value":2},{"source":"25937","target":"209207","teamId":3795,"value":2},{"source":"112377","target":"26433","teamId":3795,"value":2},{"source":"26433","target":"382275243","teamId":3795,"value":2},{"source":"2886625891","target":"209207","teamId":3795,"value":2},{"source":"209207","target":"25616149053","teamId":3795,"value":2},{"source":"295761","target":"28314","teamId":3795,"value":2},{"source":"382275243","target":"2886625891","teamId":3795,"value":2},{"source":"25937","target":"25616149053","teamId":3795,"value":2},{"source":"26433","target":"2886625891","teamId":3795,"value":2},{"source":"25616149053","target":"295761","teamId":3795,"value":2},{"source":"2886625891","target":"382275243","teamId":3795,"value":2},{"source":"28314","target":"29641","teamId":3795,"value":2},{"source":"382275243","target":"25616149053","teamId":3795,"value":2},{"source":"112377","target":"29641","teamId":3795,"value":2},{"source":"112377","target":"209207","teamId":3795,"value":2},{"source":"29641","target":"25937","teamId":3795,"value":2},{"source":"112377","target":"25937","teamId":3795,"value":2},{"source":"29641","target":"382275243","teamId":3795,"value":2},{"source":"295761","target":"25616149053","teamId":3795,"value":2},{"source":"295761","target":"25937","teamId":3795,"value":2},{"source":"209207","target":"2886625891","teamId":3795,"value":2},{"source":"29641","target":"295761","teamId":3795,"value":2},{"source":"25937","target":"29641","teamId":3795,"value":2},{"source":"25937","target":"2886625891","teamId":3795,"value":3},{"source":"382275243","target":"295761","teamId":3795,"value":3},{"source":"28314","target":"112377","teamId":3795,"value":3},{"source":"28314","target":"209207","teamId":3795,"value":3},{"source":"295761","target":"26433","teamId":3795,"value":3},{"source":"29641","target":"25616149053","teamId":3795,"value":3},{"source":"209207","target":"25937","teamId":3795,"value":3},{"source":"25616149053","target":"2886625891","teamId":3795,"value":3},{"source":"2886625891","target":"295761","teamId":3795,"value":3},{"source":"25616149053","target":"28314","teamId":3795,"value":3},{"source":"295761","target":"2886625891","teamId":3795,"value":3},{"source":"25937","target":"382275243","teamId":3795,"value":3},{"source":"2886625891","target":"26433","teamId":3795,"value":3},{"source":"29641","target":"28314","teamId":3795,"value":3},{"source":"25616149053","target":"25937","teamId":3795,"value":3},{"source":"295761","target":"29641","teamId":3795,"value":3},{"source":"25521","target":"28314","teamId":3795,"value":3},{"source":"28314","target":"25521","teamId":3795,"value":4},{"source":"209207","target":"295761","teamId":3795,"value":4},{"source":"25521","target":"209207","teamId":3795,"value":4},{"source":"209207","target":"28314","teamId":3795,"value":4},{"source":"28314","target":"25616149053","teamId":3795,"value":5},{"source":"28314","target":"25937","teamId":3795,"value":5},{"source":"29641","target":"209207","teamId":3795,"value":5},{"source":"26433","target":"295761","teamId":3795,"value":5},{"source":"25616149053","target":"29641","teamId":3795,"value":5},{"source":"25937","target":"28314","teamId":3795,"value":6},{"source":"25616149053","target":"209207","teamId":3795,"value":6},{"source":"209207","target":"29641","teamId":3795,"value":6},{"source":"25937","target":"26433","teamId":3795,"value":7}],"3767":[{"source":"347200","target":"231138","teamId":3767,"value":1},{"source":"25418","target":"25439209117","teamId":3767,"value":1},{"source":"20394","target":"347200","teamId":3767,"value":1},{"source":"20394","target":"14862","teamId":3767,"value":1},{"source":"37824","target":"25418","teamId":3767,"value":1},{"source":"25418","target":"3315","teamId":3767,"value":1},{"source":"37824","target":"231138","teamId":3767,"value":1},{"source":"25418","target":"14862","teamId":3767,"value":1},{"source":"37824","target":"134540","teamId":3767,"value":1},{"source":"37824","target":"14862","teamId":3767,"value":1},{"source":"25418","target":"37824","teamId":3767,"value":1},{"source":"347200","target":"37824","teamId":3767,"value":1},{"source":"25439209117","target":"25418","teamId":3767,"value":1},{"source":"33343314","target":"134540","teamId":3767,"value":1},{"source":"231138","target":"37824","teamId":3767,"value":2},{"source":"14862","target":"3315","teamId":3767,"value":2},{"source":"347200","target":"33343314","teamId":3767,"value":2},{"source":"20394","target":"134540","teamId":3767,"value":2},{"source":"231138","target":"356237471774","teamId":3767,"value":2},{"source":"356237471774","target":"347200","teamId":3767,"value":2},{"source":"3315","target":"25418","teamId":3767,"value":2},{"source":"347200","target":"356237471774","teamId":3767,"value":3},{"source":"37824","target":"25439209117","teamId":3767,"value":3},{"source":"134540","target":"356237471774","teamId":3767,"value":3},{"source":"37824","target":"347200","teamId":3767,"value":3},{"source":"3315","target":"14862","teamId":3767,"value":3},{"source":"33343314","target":"231138","teamId":3767,"value":3},{"source":"231138","target":"14862","teamId":3767,"value":4},{"source":"14862","target":"356237471774","teamId":3767,"value":4},{"source":"356237471774","target":"14862","teamId":3767,"value":4},{"source":"14862","target":"134540","teamId":3767,"value":4},{"source":"14862","target":"20394","teamId":3767,"value":4},{"source":"347200","target":"14862","teamId":3767,"value":4},{"source":"231138","target":"25418","teamId":3767,"value":4},{"source":"14862","target":"347200","teamId":3767,"value":5},{"source":"3315","target":"347200","teamId":3767,"value":5},{"source":"3315","target":"134540","teamId":3767,"value":5},{"source":"20394","target":"25418","teamId":3767,"value":5},{"source":"25439209117","target":"134540","teamId":3767,"value":5},{"source":"356237471774","target":"20394","teamId":3767,"value":5},{"source":"231138","target":"347200","teamId":3767,"value":6},{"source":"356237471774","target":"3315","teamId":3767,"value":6},{"source":"25418","target":"231138","teamId":3767,"value":6},{"source":"134540","target":"14862","teamId":3767,"value":6},{"source":"25439209117","target":"20394","teamId":3767,"value":6},{"source":"14862","target":"33343314","teamId":3767,"value":6},{"source":"134540","target":"25439209117","teamId":3767,"value":6},{"source":"37824","target":"3315","teamId":3767,"value":7},{"source":"134540","target":"3315","teamId":3767,"value":7},{"source":"25439209117","target":"347200","teamId":3767,"value":7},{"source":"356237471774","target":"134540","teamId":3767,"value":7},{"source":"14862","target":"37824","teamId":3767,"value":7},{"source":"356237471774","target":"231138","teamId":3767,"value":7},{"source":"25439209117","target":"14862","teamId":3767,"value":8},{"source":"347200","target":"134540","teamId":3767,"value":8},{"source":"33343314","target":"25439209117","teamId":3767,"value":8},{"source":"37824","target":"356237471774","teamId":3767,"value":8},{"source":"347200","target":"3315","teamId":3767,"value":8},{"source":"25439209117","target":"33343314","teamId":3767,"value":8},{"source":"3315","target":"231138","teamId":3767,"value":8},{"source":"3315","target":"20394","teamId":3767,"value":8},{"source":"134540","target":"347200","teamId":3767,"value":9},{"source":"33343314","target":"3315","teamId":3767,"value":9},{"source":"25418","target":"20394","teamId":3767,"value":9},{"source":"3315","target":"356237471774","teamId":3767,"value":9},{"source":"231138","target":"134540","teamId":3767,"value":9},{"source":"134540","target":"231138","teamId":3767,"value":9},{"source":"14862","target":"25439209117","teamId":3767,"value":9},{"source":"20394","target":"25439209117","teamId":3767,"value":9},{"source":"33343314","target":"20394","teamId":3767,"value":9},{"source":"231138","target":"3315","teamId":3767,"value":9},{"source":"356237471774","target":"37824","teamId":3767,"value":10},{"source":"33343314","target":"14862","teamId":3767,"value":10},{"source":"33343314","target":"356237471774","teamId":3767,"value":10},{"source":"20394","target":"356237471774","teamId":3767,"value":11},{"source":"347200","target":"25439209117","teamId":3767,"value":11},{"source":"25439209117","target":"37824","teamId":3767,"value":11},{"source":"3315","target":"37824","teamId":3767,"value":12},{"source":"356237471774","target":"25439209117","teamId":3767,"value":12},{"source":"20394","target":"231138","teamId":3767,"value":12},{"source":"356237471774","target":"33343314","teamId":3767,"value":13},{"source":"20394","target":"33343314","teamId":3767,"value":13},{"source":"20394","target":"37824","teamId":3767,"value":13},{"source":"20394","target":"3315","teamId":3767,"value":14},{"source":"231138","target":"25439209117","teamId":3767,"value":14},{"source":"25439209117","target":"231138","teamId":3767,"value":14},{"source":"3315","target":"33343314","teamId":3767,"value":14},{"source":"25439209117","target":"356237471774","teamId":3767,"value":15},{"source":"37824","target":"20394","teamId":3767,"value":15},{"source":"3315","target":"25439209117","teamId":3767,"value":17},{"source":"33343314","target":"37824","teamId":3767,"value":17},{"source":"231138","target":"20394","teamId":3767,"value":18},{"source":"25439209117","target":"3315","teamId":3767,"value":19},{"source":"37824","target":"33343314","teamId":3767,"value":28}]},"stats":{"global":{"passes":{"min":1,"max":28}},"home":{"passes":{"min":1,"max":7}},"away":{"passes":{"min":1,"max":28}}}}