{"matchId":2576055,"label":"Internazionale - Sampdoria, 3 - 2","teamsInfo":{"3161":{"city":"Milano","name":"Internazionale","wyId":3161,"officialName":"FC Internazionale Milano","area":{"name":"Italy","id":"380","alpha3code":"ITA","alpha2code":"IT"},"type":"club"},"3164":{"city":"Genova","name":"Sampdoria","wyId":3164,"officialName":"UC Sampdoria","area":{"name":"Italy","id":"380","alpha3code":"ITA","alpha2code":"IT"},"type":"club"}},"matchInfo":{"winner":3161,"homeAway":{"home":3161,"away":3164},"competitionId":524,"gameweek":10,"duration":"Regular","seasonId":181248,"roundId":4406278,"groupName":null,"status":"Played","venue":"Stadio Giuseppe Meazza","dateutc":"2017-10-24 18:45:00","homeAwayId":{"3161":"home","3164":"away"}},"nodes":{"3164":[{"id":"99833","pos":"99833","shortName":["B. Bereszy\u0144ski"],"currentNationalTeamId":3164,"averagePos":[84.788734,48.323944091796875]},{"id":"20869","pos":"20869","shortName":["N. Murru"],"currentNationalTeamId":3164,"averagePos":[14.373135,48.88059616088867]},{"id":"333571","pos":"333571","shortName":["L. Torreira"],"currentNationalTeamId":3164,"averagePos":[48.7907,49.74418640136719]},{"id":"20632","pos":"20632","shortName":["C. Puggioni"],"currentNationalTeamId":3164,"averagePos":[54.545456,90.40909099578857]},{"id":"20811","pos":"20811","shortName":["M. Silvestre"],"currentNationalTeamId":3164,"averagePos":[67.46988,64.20481872558594]},{"id":"2068921376","pos":"2068921376","shortName":["G. Caprari","G. Ram\u00edrez"],"currentNationalTeamId":3164,"averagePos":[46.07843,38.313724517822266]},{"id":"37739","pos":"37739","shortName":["D. Praet"],"currentNationalTeamId":3164,"averagePos":[51.774193,44.89247131347656]},{"id":"13817420816","pos":"13817420816","shortName":["K. Linetty","\u00c9. Barreto"],"currentNationalTeamId":3164,"averagePos":[52.371136,45.31958770751953]},{"id":"20479","pos":"20479","shortName":["F. Quagliarella"],"currentNationalTeamId":3164,"averagePos":[60.77778,35.69444274902344]},{"id":"22270","pos":"22270","shortName":["G. Ferrari"],"currentNationalTeamId":3164,"averagePos":[33.80263,62.69736862182617]},{"id":"86243240042","pos":"86243240042","shortName":["D. Zapata","D. Kownacki"],"currentNationalTeamId":3164,"averagePos":[35.305557,31.833335876464844]}],"3161":[{"id":"20571","pos":"20571","shortName":["S. Handanovi\u010d"],"currentNationalTeamId":3161,"averagePos":[52.225807,90.87096786499023]},{"id":"205177982","pos":"205177982","shortName":["Y. Nagatomo","D. Santon"],"currentNationalTeamId":3161,"averagePos":[14.313953,64.61627960205078]},{"id":"3431","pos":"3431","shortName":["Jo\u00e3o Miranda"],"currentNationalTeamId":3161,"averagePos":[28.082191,72.82191848754883]},{"id":"241676","pos":"241676","shortName":["R. Gagliardini"],"currentNationalTeamId":3161,"averagePos":[42.27778,57.56944274902344]},{"id":"11634970965","pos":"11634970965","shortName":["M. Vecino","Jo\u00e3o M\u00e1rio"],"currentNationalTeamId":3161,"averagePos":[65.978264,54.21739196777344]},{"id":"14812","pos":"14812","shortName":["I. Peri\u0161i\u0107"],"currentNationalTeamId":3161,"averagePos":[26.574469,40.87234115600586]},{"id":"138408","pos":"138408","shortName":["M. \u0160kriniar"],"currentNationalTeamId":3161,"averagePos":[68.27536,65.60869598388672]},{"id":"20631420626","pos":"20631420626","shortName":["Eder","M. Icardi"],"currentNationalTeamId":3161,"averagePos":[46.15625,40.46875]},{"id":"3543","pos":"3543","shortName":["Borja Valero"],"currentNationalTeamId":3161,"averagePos":[60.11111,42.75308609008789]},{"id":"21094","pos":"21094","shortName":["D. D'Ambrosio"],"currentNationalTeamId":3161,"averagePos":[83.097565,60.82926940917969]},{"id":"20556","pos":"20556","shortName":["A. Candreva"],"currentNationalTeamId":3161,"averagePos":[87.85149,41.178218841552734]}]},"links":{"3161":[{"source":"20571","target":"14812","teamId":3161,"value":1},{"source":"20571","target":"241676","teamId":3161,"value":1},{"source":"20571","target":"3431","teamId":3161,"value":1},{"source":"20556","target":"241676","teamId":3161,"value":1},{"source":"11634970965","target":"241676","teamId":3161,"value":1},{"source":"20571","target":"21094","teamId":3161,"value":1},{"source":"14812","target":"3431","teamId":3161,"value":1},{"source":"20571","target":"205177982","teamId":3161,"value":1},{"source":"3543","target":"20571","teamId":3161,"value":1},{"source":"21094","target":"14812","teamId":3161,"value":1},{"source":"20556","target":"20631420626","teamId":3161,"value":1},{"source":"20631420626","target":"241676","teamId":3161,"value":1},{"source":"14812","target":"138408","teamId":3161,"value":1},{"source":"241676","target":"20631420626","teamId":3161,"value":1},{"source":"20631420626","target":"3431","teamId":3161,"value":1},{"source":"20556","target":"20571","teamId":3161,"value":1},{"source":"21094","target":"205177982","teamId":3161,"value":1},{"source":"14812","target":"20556","teamId":3161,"value":1},{"source":"11634970965","target":"14812","teamId":3161,"value":2},{"source":"205177982","target":"138408","teamId":3161,"value":2},{"source":"20631420626","target":"20556","teamId":3161,"value":2},{"source":"205177982","target":"11634970965","teamId":3161,"value":2},{"source":"21094","target":"241676","teamId":3161,"value":2},{"source":"14812","target":"3543","teamId":3161,"value":2},{"source":"205177982","target":"20556","teamId":3161,"value":2},{"source":"11634970965","target":"3431","teamId":3161,"value":2},{"source":"3543","target":"3431","teamId":3161,"value":2},{"source":"21094","target":"20571","teamId":3161,"value":2},{"source":"241676","target":"14812","teamId":3161,"value":2},{"source":"3543","target":"241676","teamId":3161,"value":2},{"source":"3431","target":"21094","teamId":3161,"value":2},{"source":"20631420626","target":"14812","teamId":3161,"value":2},{"source":"3543","target":"20631420626","teamId":3161,"value":2},{"source":"14812","target":"11634970965","teamId":3161,"value":2},{"source":"20556","target":"14812","teamId":3161,"value":2},{"source":"3543","target":"11634970965","teamId":3161,"value":2},{"source":"138408","target":"3543","teamId":3161,"value":2},{"source":"20556","target":"205177982","teamId":3161,"value":3},{"source":"21094","target":"138408","teamId":3161,"value":3},{"source":"205177982","target":"3543","teamId":3161,"value":3},{"source":"14812","target":"205177982","teamId":3161,"value":3},{"source":"138408","target":"20571","teamId":3161,"value":3},{"source":"20571","target":"11634970965","teamId":3161,"value":3},{"source":"3431","target":"138408","teamId":3161,"value":3},{"source":"138408","target":"205177982","teamId":3161,"value":3},{"source":"20571","target":"3543","teamId":3161,"value":3},{"source":"21094","target":"3543","teamId":3161,"value":3},{"source":"3431","target":"11634970965","teamId":3161,"value":3},{"source":"20631420626","target":"3543","teamId":3161,"value":3},{"source":"20571","target":"138408","teamId":3161,"value":3},{"source":"241676","target":"21094","teamId":3161,"value":3},{"source":"21094","target":"20631420626","teamId":3161,"value":3},{"source":"14812","target":"20631420626","teamId":3161,"value":4},{"source":"241676","target":"11634970965","teamId":3161,"value":4},{"source":"3543","target":"205177982","teamId":3161,"value":4},{"source":"14812","target":"21094","teamId":3161,"value":4},{"source":"11634970965","target":"20631420626","teamId":3161,"value":4},{"source":"241676","target":"3543","teamId":3161,"value":4},{"source":"138408","target":"21094","teamId":3161,"value":4},{"source":"20631420626","target":"11634970965","teamId":3161,"value":4},{"source":"205177982","target":"20631420626","teamId":3161,"value":4},{"source":"3431","target":"20571","teamId":3161,"value":4},{"source":"241676","target":"20556","teamId":3161,"value":5},{"source":"14812","target":"241676","teamId":3161,"value":5},{"source":"3543","target":"21094","teamId":3161,"value":5},{"source":"138408","target":"241676","teamId":3161,"value":5},{"source":"241676","target":"3431","teamId":3161,"value":5},{"source":"20556","target":"138408","teamId":3161,"value":6},{"source":"11634970965","target":"138408","teamId":3161,"value":6},{"source":"205177982","target":"20571","teamId":3161,"value":6},{"source":"241676","target":"205177982","teamId":3161,"value":7},{"source":"241676","target":"138408","teamId":3161,"value":7},{"source":"3543","target":"14812","teamId":3161,"value":7},{"source":"205177982","target":"14812","teamId":3161,"value":7},{"source":"205177982","target":"241676","teamId":3161,"value":8},{"source":"3431","target":"241676","teamId":3161,"value":8},{"source":"21094","target":"11634970965","teamId":3161,"value":8},{"source":"11634970965","target":"21094","teamId":3161,"value":9},{"source":"20556","target":"3543","teamId":3161,"value":9},{"source":"138408","target":"11634970965","teamId":3161,"value":10},{"source":"11634970965","target":"3543","teamId":3161,"value":10},{"source":"20556","target":"11634970965","teamId":3161,"value":10},{"source":"205177982","target":"3431","teamId":3161,"value":10},{"source":"11634970965","target":"20556","teamId":3161,"value":10},{"source":"138408","target":"3431","teamId":3161,"value":11},{"source":"20556","target":"21094","teamId":3161,"value":13},{"source":"3543","target":"20556","teamId":3161,"value":17},{"source":"21094","target":"20556","teamId":3161,"value":18},{"source":"3431","target":"205177982","teamId":3161,"value":20}],"3164":[{"source":"86243240042","target":"99833","teamId":3164,"value":1},{"source":"20869","target":"99833","teamId":3164,"value":1},{"source":"20632","target":"37739","teamId":3164,"value":1},{"source":"86243240042","target":"20479","teamId":3164,"value":1},{"source":"99833","target":"2068921376","teamId":3164,"value":1},{"source":"99833","target":"22270","teamId":3164,"value":1},{"source":"86243240042","target":"22270","teamId":3164,"value":1},{"source":"22270","target":"20479","teamId":3164,"value":1},{"source":"20869","target":"86243240042","teamId":3164,"value":1},{"source":"2068921376","target":"20869","teamId":3164,"value":1},{"source":"22270","target":"2068921376","teamId":3164,"value":1},{"source":"2068921376","target":"20811","teamId":3164,"value":1},{"source":"20811","target":"20479","teamId":3164,"value":1},{"source":"20869","target":"20632","teamId":3164,"value":1},{"source":"22270","target":"99833","teamId":3164,"value":1},{"source":"333571","target":"20479","teamId":3164,"value":1},{"source":"99833","target":"86243240042","teamId":3164,"value":1},{"source":"20479","target":"86243240042","teamId":3164,"value":1},{"source":"20869","target":"20479","teamId":3164,"value":1},{"source":"20811","target":"2068921376","teamId":3164,"value":1},{"source":"333571","target":"2068921376","teamId":3164,"value":2},{"source":"86243240042","target":"13817420816","teamId":3164,"value":2},{"source":"20479","target":"20811","teamId":3164,"value":2},{"source":"20479","target":"22270","teamId":3164,"value":2},{"source":"20632","target":"99833","teamId":3164,"value":2},{"source":"20479","target":"37739","teamId":3164,"value":2},{"source":"22270","target":"86243240042","teamId":3164,"value":2},{"source":"2068921376","target":"86243240042","teamId":3164,"value":2},{"source":"99833","target":"20632","teamId":3164,"value":2},{"source":"22270","target":"20632","teamId":3164,"value":2},{"source":"86243240042","target":"2068921376","teamId":3164,"value":2},{"source":"2068921376","target":"99833","teamId":3164,"value":2},{"source":"20811","target":"20869","teamId":3164,"value":2},{"source":"86243240042","target":"333571","teamId":3164,"value":3},{"source":"333571","target":"20811","teamId":3164,"value":3},{"source":"333571","target":"86243240042","teamId":3164,"value":3},{"source":"20479","target":"13817420816","teamId":3164,"value":3},{"source":"20632","target":"20869","teamId":3164,"value":3},{"source":"20479","target":"99833","teamId":3164,"value":3},{"source":"37739","target":"22270","teamId":3164,"value":3},{"source":"37739","target":"333571","teamId":3164,"value":3},{"source":"2068921376","target":"37739","teamId":3164,"value":3},{"source":"37739","target":"20479","teamId":3164,"value":3},{"source":"22270","target":"37739","teamId":3164,"value":3},{"source":"99833","target":"20479","teamId":3164,"value":3},{"source":"20869","target":"2068921376","teamId":3164,"value":3},{"source":"86243240042","target":"20869","teamId":3164,"value":3},{"source":"20632","target":"22270","teamId":3164,"value":4},{"source":"20479","target":"2068921376","teamId":3164,"value":4},{"source":"13817420816","target":"86243240042","teamId":3164,"value":4},{"source":"333571","target":"99833","teamId":3164,"value":4},{"source":"20811","target":"37739","teamId":3164,"value":4},{"source":"333571","target":"22270","teamId":3164,"value":4},{"source":"2068921376","target":"20479","teamId":3164,"value":4},{"source":"86243240042","target":"37739","teamId":3164,"value":4},{"source":"13817420816","target":"20479","teamId":3164,"value":4},{"source":"37739","target":"13817420816","teamId":3164,"value":4},{"source":"13817420816","target":"20869","teamId":3164,"value":4},{"source":"99833","target":"333571","teamId":3164,"value":4},{"source":"13817420816","target":"20811","teamId":3164,"value":5},{"source":"20869","target":"13817420816","teamId":3164,"value":5},{"source":"13817420816","target":"22270","teamId":3164,"value":5},{"source":"20869","target":"333571","teamId":3164,"value":5},{"source":"2068921376","target":"13817420816","teamId":3164,"value":5},{"source":"13817420816","target":"37739","teamId":3164,"value":5},{"source":"20811","target":"333571","teamId":3164,"value":5},{"source":"37739","target":"86243240042","teamId":3164,"value":5},{"source":"13817420816","target":"2068921376","teamId":3164,"value":6},{"source":"20869","target":"22270","teamId":3164,"value":6},{"source":"2068921376","target":"333571","teamId":3164,"value":6},{"source":"99833","target":"13817420816","teamId":3164,"value":6},{"source":"13817420816","target":"99833","teamId":3164,"value":6},{"source":"99833","target":"37739","teamId":3164,"value":6},{"source":"37739","target":"2068921376","teamId":3164,"value":7},{"source":"20811","target":"20632","teamId":3164,"value":7},{"source":"333571","target":"20869","teamId":3164,"value":7},{"source":"20811","target":"13817420816","teamId":3164,"value":7},{"source":"37739","target":"20869","teamId":3164,"value":7},{"source":"37739","target":"20811","teamId":3164,"value":7},{"source":"20811","target":"99833","teamId":3164,"value":7},{"source":"22270","target":"333571","teamId":3164,"value":7},{"source":"37739","target":"99833","teamId":3164,"value":7},{"source":"22270","target":"13817420816","teamId":3164,"value":7},{"source":"22270","target":"20869","teamId":3164,"value":8},{"source":"22270","target":"20811","teamId":3164,"value":8},{"source":"13817420816","target":"333571","teamId":3164,"value":9},{"source":"20869","target":"37739","teamId":3164,"value":9},{"source":"333571","target":"13817420816","teamId":3164,"value":10},{"source":"333571","target":"37739","teamId":3164,"value":10},{"source":"20811","target":"22270","teamId":3164,"value":10},{"source":"99833","target":"20811","teamId":3164,"value":13}]},"stats":{"global":{"passes":{"min":1,"max":20}},"home":{"passes":{"min":1,"max":20}},"away":{"passes":{"min":1,"max":13}}}}